prusa/connect/printer/__init__.py
prusa/connect/printer/camera.py
prusa/connect/printer/camera_configurator.py
prusa/connect/printer/camera_controller.py
prusa/connect/printer/camera_driver.py
prusa/connect/printer/clock.py
prusa/connect/printer/command.py
prusa/connect/printer/conditions.py
prusa/connect/printer/const.py
prusa/connect/printer/download.py
prusa/connect/printer/errors.py
prusa/connect/printer/files.py
prusa/connect/printer/models.py
prusa/connect/printer/py.typed
prusa/connect/printer/util.py
prusa.connect.sdk.printer-0.8.1.data/data/share/doc/prusa-connect-printer/ChangeLog
prusa.connect.sdk.printer-0.8.1.data/data/share/doc/prusa-connect-printer/README.rst
prusa.connect.sdk.printer-0.8.1.dist-info/METADATA
prusa.connect.sdk.printer-0.8.1.dist-info/WHEEL
prusa.connect.sdk.printer-0.8.1.dist-info/top_level.txt
prusa.connect.sdk.printer-0.8.1.dist-info/RECORD
