Metadata-Version: 2.1
Name: prusa.connect.sdk.printer
Version: 0.8.1
Summary: Python printer library for PrusaConnect
Home-page: https://github.com/prusa3d/Prusa-Connect-SDK-Printer
Author: Prusa Link Developers
Author-email: Prusa Link Developers <link@prusa3d.cz>
Maintainer: Prusa Link Developers
Maintainer-email: Ondřej Tůma <mcbig@zeropage.cz>, Michal Zoubek <michal.zoubek@prusa3d.cz>, Tomáš Jozífek <jozifektomas@gmail.com>
License: Freeware
Project-URL: Repository, https://github.com/prusa3d/Prusa-Connect-SDK-Printer
Project-URL: Bug Tracker, https://github.com/prusa3d/Prusa-Connect-SDK-Printer/issues
Classifier: Development Status :: 5 - Production/Stable
Classifier: Intended Audience :: Developers
Classifier: Natural Language :: English
Classifier: License :: Freeware
Classifier: Operating System :: POSIX
Classifier: Programming Language :: Python :: 3
Classifier: Topic :: Software Development :: Libraries :: Python Modules
Requires-Python: >=3.9
Requires-Dist: py-gcode-metadata >=0.2.0
Requires-Dist: requests >=2.31.0
Requires-Dist: inotify-simple ~=1.3.5
Requires-Dist: mypy-extensions ~=1.0.0
Requires-Dist: urllib3 <3,>=1.21.1
